{
  "ComponentIndexes": {},
  "ControlUniqueIds": {
    "App": 1,
    "Screen1": 3
  },
  "FunctionParamsInvariantScripts": {},
  "HeaderLastSavedDateTimeUTC": "01/12/2022 17:08:51",
  "LocalDatabaseReferencesAsEmpty": false,
  "LocalResourceFileNames": {},
  "LocalResourceRootPaths": {},
  "OrderComponentMetadata": {},
  "OrderComponentTemplate": {},
  "OrderDataSource": {},
  "OrderGroupControls": {},
  "OrderTemplate": {},
  "OrderXMLTemplate": {},
  "PublishOrderIndices": {
    "App": 0,
    "Screen1": 0
  },
  "ResourcesJsonIndices": {},
  "TemplateVersions": {},
  "VolatileProperties": {
    "AnalysisLoadTime": 0.0179781,
    "ControlCount": {},
    "ErrorCount": 0
  }
}